MLABvo/Bolidozor.py
MLABvo/BolidozorTools.py
MLABvo/__init__.py
MLABvo-0.0.3.dist-info/DESCRIPTION.rst
MLABvo-0.0.3.dist-info/METADATA
MLABvo-0.0.3.dist-info/RECORD
MLABvo-0.0.3.dist-info/WHEEL
MLABvo-0.0.3.dist-info/metadata.json
MLABvo-0.0.3.dist-info/top_level.txt
